Workbook
Name F_ACHATS: CALCULS!$I$7:$I$30
Name F_ACTU: CALCULS!$K$7:$K$30
Name F_CA_USD: CALCULS!$F$7:$F$30
Name F_CHARGES_USD: CALCULS!$G$7:$G$30
Name F_CUMUL: CALCULS!$M$6:$M$30
Name F_FLUX: CALCULS!$J$6:$J$30
Name F_FLUX1: CALCULS!$J$7:$J$30
Name F_MARGE_USD: CALCULS!$H$7:$H$30
Name F_TAUX: CALCULS!$B$7:$B$30
Name F_VOLUME: CALCULS!$C$7:$C$30
Name H_ACTUALISATION: HYPOTHESES!$B$18
Name H_AMENAGEMENT: HYPOTHESES!$B$5
Name H_AUTRES_XOF: HYPOTHESES!$B$15
Name H_COUT_USD: HYPOTHESES!$B$12
Name H_DERIVE_TAUX: HYPOTHESES!$B$17
Name H_LOYER_XOF: HYPOTHESES!$B$13
Name H_MATERIEL: HYPOTHESES!$B$6
Name H_MONTEE: HYPOTHESES!$B$10
Name H_PERSONNEL_XOF: HYPOTHESES!$B$14
Name H_PRIX_XOF: HYPOTHESES!$B$11
Name H_STOCK_INITIAL: HYPOTHESES!$B$7
Name H_TAUX_XOF: HYPOTHESES!$B$16
Name H_VOLUME_CROISIERE: HYPOTHESES!$B$9
Name H_VOLUME_M1: HYPOTHESES!$B$8
Name LIBRE_ANALYSE: ANALYSE!$A$1:$U$60
Name LIBRE_CALCULS: CALCULS!$A$1:$M$30
Name LIBRE_CLEAN: CLEAN!$A$1:$H$40
Name LIBRE_DASHBOARD: DASHBOARD!$A$1:$H$40
Name R_CONTROLE: REPONSES!$B$36
Name R_ECART_TAUX: REPONSES!$B$35
Name S_FLUX_OPT: ANALYSE!$D$7:$D$30
Name S_FLUX_PESS: ANALYSE!$B$7:$B$30
Name Z_AUDIT: CALCULS!$A$6:$M$30

Sheet README
A1: README
A3: À quoi sert ce classeur | B3: Décider de l'ouverture d'une septième agence BAOBAB à Bamako (Mali). Horizon 24 mois, du 1er janvier 2027 au 31 décembre 2028.
A4: Qui l'a produit, et quand | B4: Direction financière BAOBAB, septembre 2026. Version 1.0.
A5: Les sources | B5: Les investissements viennent des trois devis reçus en août 2026. La montée en charge est calibrée sur l'ouverture de Libreville (feuilles RAW et CLEAN) : 95 % de la croisière atteints au mois 13, retenu à 14 mois pour Bamako, le marché malien étant moins dense.
A6: La règle des couleurs | B6: Bleu = une saisie, et toutes les saisies sont sur HYPOTHESES. Noir = une formule. Vert = un lien vers une autre feuille du classeur. Rouge = un lien vers un autre classeur — il n'y en a aucun ici, et c'est voulu.
A7: Pourquoi le taux de change est au centre | B7: On encaisse en francs CFA et on décaisse en dollars : le stock est importé et payé par le groupe. Le résultat en dollars dépend donc directement du taux. Et le franc CFA n'est pas une devise flottante : il est arrimé à l'euro à parité fixe (655,957 XOF pour 1 EUR). Le « risque de change » de ce plan est en réalité un risque EUR/USD, que personne à Bamako ne pilote.
A8: VAN — définition | B8: Somme des flux mensuels actualisés des mois 1 à 24, moins l'investissement du mois 0. Taux d'actualisation : 14 % par an, exigé par la direction, converti en taux mensuel équivalent.
A9: TRI — définition | B9: Taux qui annule la VAN. Calculé sur les flux mensuels, mois 0 inclus, puis annualisé. Il n'a de sens que parce que les flux changent de signe une seule fois.
A10: Taux limite — définition | B10: Taux de change de départ au-delà duquel la VAN devient négative, à dérive et volumes inchangés. Lu par Valeur cible, et recalculé par formule : la VAN vaut (valeur actuelle des encaissements CFA) / taux − (valeur actuelle des décaissements USD).
A11: Comment actualiser ce classeur | B11: Changer les valeurs bleues de HYPOTHESES, rien d'autre. Vérifier ensuite que les huit contrôles de QUALITE passent, et que REPONSES!B34 vaut toujours zéro. Une seule borne : H_MONTEE doit valoir au moins 2 — la courbe de montée en charge divise par (H_MONTEE − 1), et rendrait #DIV/0! à 1. Le cas n'a pas été corrigé : il a été écrit ici.
A12: Les deux natures de flux, et pourquoi elles sont séparées | B12: CALCULS sépare volontairement la marge locale (encaissée en XOF, donc sensible au taux) des achats (décaissés en USD, donc insensibles). Ce n'est pas une redondance : c'est ce qui permet d'écrire la VAN sous la forme entrées/taux − sorties, et donc d'inverser la formule pour trouver le taux de bascule sans tâtonner.
A13: Ce que ce modèle ne dit pas | B13: Il ne dit rien du besoin en fonds de roulement au-delà du stock initial, rien de la fiscalité malienne, rien du risque de sécurité. Trois trous connus, écrits ici pour qu'on ne les découvre pas en réunion.

Sheet HYPOTHESES
A1: Les quatorze hypothèses
A2: Tout ce que ce plan suppose est ici, et nulle part ailleurs. Une cellule bleue hors de cette feuille est un bug.
A4: Code | B4: Valeur | C4: Ce que c'est
A5: H_AMENAGEMENT | B5: 68000 | C5: Aménagement du local — cloisons, rayonnage, groupe électrogène
A6: H_MATERIEL | B6: 41500 | C6: Matériel roulant et informatique — une camionnette, six postes
A7: H_STOCK_INITIAL | B7: 95000 | C7: Stock initial — payé en dollars, comme tous les achats du groupe
A8: H_VOLUME_M1 | B8: 4200 | C8: Volume du premier mois, en unités
A9: H_VOLUME_CROISIERE | B9: 19500 | C9: Volume de croisière, en unités par mois
A10: H_MONTEE | B10: 14 | C10: Durée de la montée en charge, en mois — calibrée sur Libreville
A11: H_PRIX_XOF | B11: 4350 | C11: Prix de vente moyen par unité — encaissé en francs CFA
A12: H_COUT_USD | B12: 4.55 | C12: Coût d'achat moyen par unité — décaissé en dollars
A13: H_LOYER_XOF | B13: 2750000 | C13: Loyer mensuel du local
A14: H_PERSONNEL_XOF | B14: 6480000 | C14: Masse salariale mensuelle — onze personnes
A15: H_AUTRES_XOF | B15: 1920000 | C15: Autres charges mensuelles — énergie, transport, assurances
A16: H_TAUX_XOF | B16: 631.4 | C16: Taux de change au démarrage, en XOF pour 1 USD
... A18: H_ACTUALISATION | B18: 0.14 | C18: Taux d'actualisation annuel exigé par la direction
A20: Les trois scénarios
A21: Scenario | B21: Volume_croisiere | C21: Prix_XOF | D21: Derive_Taux
A22: Pessimiste | B22: 16500 | C22: 4200 | D22: 0.008
A23: Base | B23: 19500 | C23: 4350 | D23: 0.0045
A24: Optimiste | B24: 22000 | C24: 4450 | D24: 0.002
A26: La ligne « Base » doit être identique aux hypothèses du haut. La feuille QUALITE le vérifie.

Sheet RAW
A1: Libreville — les 24 premiers mois, extraction brute
A2: Source : export du SI commercial, 3 septembre 2026. On n'y touche pas — on la copie vers CLEAN.
A4: Periode | B4: Mois | C4: Volume | D4: CA_XAF
A5: janv-24 | B5: 1 | C5: 4121 | D5: 16942078
A6: févr-24 | B6: 2 | C6: 5557 | D6: 22550923
A7: mars-24 | B7: 3 | C7: 6640 | D7: 27060924
A8: avr-24 | B8: 4 | C8: 7406 | D8: 31901671
A9: mai-24 | B9: 5 | C9: 8616 | D9: 34965582
A10: juin-24 | B10: 6 | C10: 9823 | D10: 41692538
A11: juil-24 | B11: 7 | C11: 11337 | D11: 45361425
A12: août-24 | B12: 8 | C12: 12005 | D12: 49322232
A13: sept-24 | B13: 9 | C13: 12518 | D13: 53061209
A14: oct-24 | B14: 10 | C14: 14058 | D14: 56160524
A15: nov-24 | B15: 11 | C15: 15901 | D15: 66320593
A16: déc-24 | B16: 12 | C16: 15917 | D16: 64041047
... A28: déc-25 | B28: 24 | C28: 17328 | D28: 70516736

Sheet CLEAN
A1: Libreville — la courbe de montée en charge
A2: C'est d'ici que sort H_MONTEE. L'hypothèse n'est pas un chiffre rond : c'est la dernière ouverture du groupe, relue.
A4: Mois | B4: Volume | C4: Part_croisiere | D4: Lecture
A5: 1 | B5: 4121 | C5: =B5/MAX($B$5:$B$28) -> 0.22374851
A6: 2 | B6: 5557 | C6: =B6/MAX($B$5:$B$28) -> 0.30171571
A7: 3 | B7: 6640 | C7: =B7/MAX($B$5:$B$28) -> 0.36051689
A8: 4 | B8: 7406 | C8: =B8/MAX($B$5:$B$28) -> 0.40210663
A9: 5 | B9: 8616 | C9: =B9/MAX($B$5:$B$28) -> 0.46780324
A10: 6 | B10: 9823 | C10: =B10/MAX($B$5:$B$28) -> 0.53333695
A11: 7 | B11: 11337 | C11: =B11/MAX($B$5:$B$28) -> 0.61553915
A12: 8 | B12: 12005 | C12: =B12/MAX($B$5:$B$28) -> 0.65180801
A13: 9 | B13: 12518 | C13: =B13/MAX($B$5:$B$28) -> 0.6796612
A14: 10 | B14: 14058 | C14: =B14/MAX($B$5:$B$28) -> 0.76327506
A15: 11 | B15: 15901 | C15: =B15/MAX($B$5:$B$28) -> 0.86334021
A16: 12 | B16: 15917 | C16: =B16/MAX($B$5:$B$28) -> 0.86420893
... A28: 24 | B28: 17328 | C28: =B28/MAX($B$5:$B$28) -> 0.94081876
A30: Volume de croisière observé | B30: 18418
A31: Mois où 95 % est atteint | B31: 13
A32: Hypothèse retenue pour Bamako | B32: 14 | D32: Un mois de plus que Libreville : le marché malien est moins dense.

Sheet CALCULS
A1: La projection sur 24 mois
A2: Une ligne par mois, le mois 0 portant l'investissement. Aucune valeur en dur : tout descend de HYPOTHESES.
A3: Taux d'actualisation mensuel | B3: =(1+H_ACTUALISATION)^(1/12)-1 -> 0.010978852
A5: Mois | B5: Taux_XOF_USD | C5: Volume | D5: CA_XOF | E5: Charges_XOF | F5: CA_USD | G5: Charges_USD | H5: Marge_locale_USD | I5: Achats_USD | J5: Flux_USD | K5: Actualisation | L5: Flux_actualise | M5: Cumul_USD
A6: =0 -> 0 | B6: =H_TAUX_XOF*(1+H_DERIVE_TAUX)^A6 -> 631.4 | C6: =0 -> 0 | D6: =C6*H_PRIX_XOF -> 0 | E6: =0 -> 0 | F6: =D6/B6 -> 0 | G6: =E6/B6 -> 0 | H6: =F6-G6 -> 0 | I6: =C6*H_COUT_USD -> 0 | J6: =-(H_AMENAGEMENT+H_MATERIEL+H_STOCK_INITIAL) -> -204500 | K6: =1/(1+$B$3)^A6 -> 1 | L6: =J6*K6 -> -204500 | M6: =J6 -> -204500
A7: =A6+1 -> 1 | B7: =H_TAUX_XOF*(1+H_DERIVE_TAUX)^A7 -> 634.2413 | C7: =MIN(H_VOLUME_CROISIERE,H_VOLUME_M1+(H_VOLUME_CROISIERE-H_VOLUME_M1)*(A7-1)/(H_MONTEE-1)) -> 4200 | D7: =C7*H_PRIX_XOF -> 18270000 | E7: =H_LOYER_XOF+H_PERSONNEL_XOF+H_AUTRES_XOF -> 11150000 | F7: =D7/B7 -> 28806.071 | G7: =E7/B7 -> 17580.06 | H7: =F7-G7 -> 11226.011 | I7: =C7*H_COUT_USD -> 19110 | J7: =H7-I7 -> -7883.9887 | K7: =1/(1+$B$3)^A7 -> 0.98914037 | L7: =J7*K7 -> -7798.3715 | M7: =M6+J7 -> -212383.99
A8: =A7+1 -> 2 | B8: =H_TAUX_XOF*(1+H_DERIVE_TAUX)^A8 -> 637.09539 | C8: =MIN(H_VOLUME_CROISIERE,H_VOLUME_M1+(H_VOLUME_CROISIERE-H_VOLUME_M1)*(A8-1)/(H_MONTEE-1)) -> 5376.9231 | D8: =C8*H_PRIX_XOF -> 23389615 | E8: =H_LOYER_XOF+H_PERSONNEL_XOF+H_AUTRES_XOF -> 11150000 | F8: =D8/B8 -> 36712.894 | G8: =E8/B8 -> 17501.304 | H8: =F8-G8 -> 19211.59 | I8: =C8*H_COUT_USD -> 24465 | J8: =H8-I8 -> -5253.4099 | K8: =1/(1+$B$3)^A8 -> 0.97839868 | L8: =J8*K8 -> -5139.9293 | M8: =M7+J8 -> -217637.4
A9: =A8+1 -> 3 | B9: =H_TAUX_XOF*(1+H_DERIVE_TAUX)^A9 -> 639.96232 | C9: =MIN(H_VOLUME_CROISIERE,H_VOLUME_M1+(H_VOLUME_CROISIERE-H_VOLUME_M1)*(A9-1)/(H_MONTEE-1)) -> 6553.8462 | D9: =C9*H_PRIX_XOF -> 28509231 | E9: =H_LOYER_XOF+H_PERSONNEL_XOF+H_AUTRES_XOF -> 11150000 | F9: =D9/B9 -> 44548.296 | G9: =E9/B9 -> 17422.901 | H9: =F9-G9 -> 27125.395 | I9: =C9*H_COUT_USD -> 29820 | J9: =H9-I9 -> -2694.6047 | K9: =1/(1+$B$3)^A9 -> 0.96777364 | L9: =J9*K9 -> -2607.7674 | M9: =M8+J9 -> -220332
A10: =A9+1 -> 4 | B10: =H_TAUX_XOF*(1+H_DERIVE_TAUX)^A10 -> 642.84215 | C10: =MIN(H_VOLUME_CROISIERE,H_VOLUME_M1+(H_VOLUME_CROISIERE-H_VOLUME_M1)*(A10-1)/(H_MONTEE-1)) -> 7730.7692 | D10: =C10*H_PRIX_XOF -> 33628846 | E10: =H_LOYER_XOF+H_PERSONNEL_XOF+H_AUTRES_XOF -> 11150000 | F10: =D10/B10 -> 52312.759 | G10: =E10/B10 -> 17344.849 | H10: =F10-G10 -> 34967.91 | I10: =C10*H_COUT_USD -> 35175 | J10: =H10-I10 -> -207.09021 | K10: =1/(1+$B$3)^A10 -> 0.95726398 | L10: =J10*K10 -> -198.24 | M10: =M9+J10 -> -220539.09
A11: =A10+1 -> 5 | B11: =H_TAUX_XOF*(1+H_DERIVE_TAUX)^A11 -> 645.73494 | C11: =MIN(H_VOLUME_CROISIERE,H_VOLUME_M1+(H_VOLUME_CROISIERE-H_VOLUME_M1)*(A11-1)/(H_MONTEE-1)) -> 8907.6923 | D11: =C11*H_PRIX_XOF -> 38748462 | E11: =H_LOYER_XOF+H_PERSONNEL_XOF+H_AUTRES_XOF -> 11150000 | F11: =D11/B11 -> 60006.76 | G11: =E11/B11 -> 17267.147 | H11: =F11-G11 -> 42739.613 | I11: =C11*H_COUT_USD -> 40530 | J11: =H11-I11 -> 2209.6135 | K11: =1/(1+$B$3)^A11 -> 0.94686845 | L11: =J11*K11 -> 2092.2133 | M11: =M10+J11 -> -218329.48
A12: =A11+1 -> 6 | B12: =H_TAUX_XOF*(1+H_DERIVE_TAUX)^A12 -> 648.64074 | C12: =MIN(H_VOLUME_CROISIERE,H_VOLUME_M1+(H_VOLUME_CROISIERE-H_VOLUME_M1)*(A12-1)/(H_MONTEE-1)) -> 10084.615 | D12: =C12*H_PRIX_XOF -> 43868077 | E12: =H_LOYER_XOF+H_PERSONNEL_XOF+H_AUTRES_XOF -> 11150000 | F12: =D12/B12 -> 67630.776 | G12: =E12/B12 -> 17189.793 | H12: =F12-G12 -> 50440.983 | I12: =C12*H_COUT_USD -> 45885 | J12: =H12-I12 -> 4555.9834 | K12: =1/(1+$B$3)^A12 -> 0.93658581 | L12: =J12*K12 -> 4267.0694 | M12: =M11+J12 -> -213773.5
A13: =A12+1 -> 7 | B13: =H_TAUX_XOF*(1+H_DERIVE_TAUX)^A13 -> 651.55963 | C13: =MIN(H_VOLUME_CROISIERE,H_VOLUME_M1+(H_VOLUME_CROISIERE-H_VOLUME_M1)*(A13-1)/(H_MONTEE-1)) -> 11261.538 | D13: =C13*H_PRIX_XOF -> 48987692 | E13: =H_LOYER_XOF+H_PERSONNEL_XOF+H_AUTRES_XOF -> 11150000 | F13: =D13/B13 -> 75185.279 | G13: =E13/B13 -> 17112.785 | H13: =F13-G13 -> 58072.494 | I13: =C13*H_COUT_USD -> 51240 | J13: =H13-I13 -> 6832.4938 | K13: =1/(1+$B$3)^A13 -> 0.92641484 | L13: =J13*K13 -> 6329.7236 | M13: =M12+J13 -> -206941
A14: =A13+1 -> 8 | B14: =H_TAUX_XOF*(1+H_DERIVE_TAUX)^A14 -> 654.49164 | C14: =MIN(H_VOLUME_CROISIERE,H_VOLUME_M1+(H_VOLUME_CROISIERE-H_VOLUME_M1)*(A14-1)/(H_MONTEE-1)) -> 12438.462 | D14: =C14*H_PRIX_XOF -> 54107308 | E14: =H_LOYER_XOF+H_PERSONNEL_XOF+H_AUTRES_XOF -> 11150000 | F14: =D14/B14 -> 82670.739 | G14: =E14/B14 -> 17036.123 | H14: =F14-G14 -> 65634.616 | I14: =C14*H_COUT_USD -> 56595 | J14: =H14-I14 -> 9039.6159 | K14: =1/(1+$B$3)^A14 -> 0.91635432 | L14: =J14*K14 -> 8283.4911 | M14: =M13+J14 -> -197901.39
A15: =A14+1 -> 9 | B15: =H_TAUX_XOF*(1+H_DERIVE_TAUX)^A15 -> 657.43686 | C15: =MIN(H_VOLUME_CROISIERE,H_VOLUME_M1+(H_VOLUME_CROISIERE-H_VOLUME_M1)*(A15-1)/(H_MONTEE-1)) -> 13615.385 | D15: =C15*H_PRIX_XOF -> 59226923 | E15: =H_LOYER_XOF+H_PERSONNEL_XOF+H_AUTRES_XOF -> 11150000 | F15: =D15/B15 -> 90087.622 | G15: =E15/B15 -> 16959.804 | H15: =F15-G15 -> 73127.818 | I15: =C15*H_COUT_USD -> 61950 | J15: =H15-I15 -> 11177.818 | K15: =1/(1+$B$3)^A15 -> 0.90640306 | L15: =J15*K15 -> 10131.609 | M15: =M14+J15 -> -186723.57
A16: =A15+1 -> 10 | B16: =H_TAUX_XOF*(1+H_DERIVE_TAUX)^A16 -> 660.39532 | C16: =MIN(H_VOLUME_CROISIERE,H_VOLUME_M1+(H_VOLUME_CROISIERE-H_VOLUME_M1)*(A16-1)/(H_MONTEE-1)) -> 14792.308 | D16: =C16*H_PRIX_XOF -> 64346538 | E16: =H_LOYER_XOF+H_PERSONNEL_XOF+H_AUTRES_XOF -> 11150000 | F16: =D16/B16 -> 97436.393 | G16: =E16/B16 -> 16883.826 | H16: =F16-G16 -> 80552.567 | I16: =C16*H_COUT_USD -> 67305 | J16: =H16-I16 -> 13247.567 | K16: =1/(1+$B$3)^A16 -> 0.89655986 | L16: =J16*K16 -> 11877.237 | M16: =M15+J16 -> -173476
A17: =A16+1 -> 11 | B17: =H_TAUX_XOF*(1+H_DERIVE_TAUX)^A17 -> 663.3671 | C17: =MIN(H_VOLUME_CROISIERE,H_VOLUME_M1+(H_VOLUME_CROISIERE-H_VOLUME_M1)*(A17-1)/(H_MONTEE-1)) -> 15969.231 | D17: =C17*H_PRIX_XOF -> 69466154 | E17: =H_LOYER_XOF+H_PERSONNEL_XOF+H_AUTRES_XOF -> 11150000 | F17: =D17/B17 -> 104717.51 | G17: =E17/B17 -> 16808.19 | H17: =F17-G17 -> 87909.325 | I17: =C17*H_COUT_USD -> 72660 | J17: =H17-I17 -> 15249.325 | K17: =1/(1+$B$3)^A17 -> 0.88682355 | L17: =J17*K17 -> 13523.46 | M17: =M16+J17 -> -158226.68
A18: =A17+1 -> 12 | B18: =H_TAUX_XOF*(1+H_DERIVE_TAUX)^A18 -> 666.35225 | C18: =MIN(H_VOLUME_CROISIERE,H_VOLUME_M1+(H_VOLUME_CROISIERE-H_VOLUME_M1)*(A18-1)/(H_MONTEE-1)) -> 17146.154 | D18: =C18*H_PRIX_XOF -> 74585769 | E18: =H_LOYER_XOF+H_PERSONNEL_XOF+H_AUTRES_XOF -> 11150000 | F18: =D18/B18 -> 111931.44 | G18: =E18/B18 -> 16732.892 | H18: =F18-G18 -> 95198.551 | I18: =C18*H_COUT_USD -> 78015 | J18: =H18-I18 -> 17183.551 | K18: =1/(1+$B$3)^A18 -> 0.87719298 | L18: =J18*K18 -> 15073.291 | M18: =M17+J18 -> -141043.13
... A30: =A29+1 -> 24 | B30: =H_TAUX_XOF*(1+H_DERIVE_TAUX)^A30 -> 703.23935 | C30: =MIN(H_VOLUME_CROISIERE,H_VOLUME_M1+(H_VOLUME_CROISIERE-H_VOLUME_M1)*(A30-1)/(H_MONTEE-1)) -> 19500 | D30: =C30*H_PRIX_XOF -> 84825000 | E30: =H_LOYER_XOF+H_PERSONNEL_XOF+H_AUTRES_XOF -> 11150000 | F30: =D30/B30 -> 120620.38 | G30: =E30/B30 -> 15855.199 | H30: =F30-G30 -> 104765.18 | I30: =C30*H_COUT_USD -> 88725 | J30: =H30-I30 -> 16040.184 | K30: =1/(1+$B$3)^A30 -> 0.76946753 | L30: =J30*K30 -> 12342.401 | M30: =M29+J30 -> 80732.206

Sheet ANALYSE
A1: Les trois scénarios, recalculés côte à côte
A2: Le Gestionnaire de scénarios explore. Ce bloc-ci documente : il reste dans le classeur, et il se recalcule.
A5: Mois | B5: Pessimiste | C5: Base | D5: Optimiste
A6: =CALCULS!A6 -> 0 | B6: =-(H_AMENAGEMENT+H_MATERIEL+H_STOCK_INITIAL) -> -204500 | C6: =-(H_AMENAGEMENT+H_MATERIEL+H_STOCK_INITIAL) -> -204500 | D6: =-(H_AMENAGEMENT+H_MATERIEL+H_STOCK_INITIAL) -> -204500
A7: =CALCULS!A7 -> 1 | B7: =(MIN(INDEX(t_Scenarios[Volume_croisiere],1),H_VOLUME_M1+(INDEX(t_Scenarios[Volume_croisiere],1)-H_VOLUME_M1)*($A7-1)/(H_MONTEE-1))*INDEX(t_Scenarios[Prix_XOF],1)-(H_LOYER_XOF+H_PERSONNEL_XOF+H_AUTRES_XOF))/(H_TAUX_XOF*(1+INDEX(t_Scenarios[Derive_Taux],1))^$A7)-MIN(INDEX(t_Scenarios[Volume_croisiere],1),H_VOLUME_M1+(INDEX(t_Scenarios[Volume_croisiere],1)-H_VOLUME_M1)*($A7-1)/(H_MONTEE-1))*H_COUT_USD -> -8912.8317 | C7: =(MIN(INDEX(t_Scenarios[Volume_croisiere],2),H_VOLUME_M1+(INDEX(t_Scenarios[Volume_croisiere],2)-H_VOLUME_M1)*($A7-1)/(H_MONTEE-1))*INDEX(t_Scenarios[Prix_XOF],2)-(H_LOYER_XOF+H_PERSONNEL_XOF+H_AUTRES_XOF))/(H_TAUX_XOF*(1+INDEX(t_Scenarios[Derive_Taux],2))^$A7)-MIN(INDEX(t_Scenarios[Volume_croisiere],2),H_VOLUME_M1+(INDEX(t_Scenarios[Volume_croisiere],2)-H_VOLUME_M1)*($A7-1)/(H_MONTEE-1))*H_COUT_USD -> -7883.9887 | D7: =(MIN(INDEX(t_Scenarios[Volume_croisiere],3),H_VOLUME_M1+(INDEX(t_Scenarios[Volume_croisiere],3)-H_VOLUME_M1)*($A7-1)/(H_MONTEE-1))*INDEX(t_Scenarios[Prix_XOF],3)-(H_LOYER_XOF+H_PERSONNEL_XOF+H_AUTRES_XOF))/(H_TAUX_XOF*(1+INDEX(t_Scenarios[Derive_Taux],3))^$A7)-MIN(INDEX(t_Scenarios[Volume_croisiere],3),H_VOLUME_M1+(INDEX(t_Scenarios[Volume_croisiere],3)-H_VOLUME_M1)*($A7-1)/(H_MONTEE-1))*H_COUT_USD -> -7192.1189
A8: =CALCULS!A8 -> 2 | B8: =(MIN(INDEX(t_Scenarios[Volume_croisiere],1),H_VOLUME_M1+(INDEX(t_Scenarios[Volume_croisiere],1)-H_VOLUME_M1)*($A8-1)/(H_MONTEE-1))*INDEX(t_Scenarios[Prix_XOF],1)-(H_LOYER_XOF+H_PERSONNEL_XOF+H_AUTRES_XOF))/(H_TAUX_XOF*(1+INDEX(t_Scenarios[Derive_Taux],1))^$A8)-MIN(INDEX(t_Scenarios[Volume_croisiere],1),H_VOLUME_M1+(INDEX(t_Scenarios[Volume_croisiere],1)-H_VOLUME_M1)*($A8-1)/(H_MONTEE-1))*H_COUT_USD -> -7104.559 | C8: =(MIN(INDEX(t_Scenarios[Volume_croisiere],2),H_VOLUME_M1+(INDEX(t_Scenarios[Volume_croisiere],2)-H_VOLUME_M1)*($A8-1)/(H_MONTEE-1))*INDEX(t_Scenarios[Prix_XOF],2)-(H_LOYER_XOF+H_PERSONNEL_XOF+H_AUTRES_XOF))/(H_TAUX_XOF*(1+INDEX(t_Scenarios[Derive_Taux],2))^$A8)-MIN(INDEX(t_Scenarios[Volume_croisiere],2),H_VOLUME_M1+(INDEX(t_Scenarios[Volume_croisiere],2)-H_VOLUME_M1)*($A8-1)/(H_MONTEE-1))*H_COUT_USD -> -5253.4099 | D8: =(MIN(INDEX(t_Scenarios[Volume_croisiere],3),H_VOLUME_M1+(INDEX(t_Scenarios[Volume_croisiere],3)-H_VOLUME_M1)*($A8-1)/(H_MONTEE-1))*INDEX(t_Scenarios[Prix_XOF],3)-(H_LOYER_XOF+H_PERSONNEL_XOF+H_AUTRES_XOF))/(H_TAUX_XOF*(1+INDEX(t_Scenarios[Derive_Taux],3))^$A8)-MIN(INDEX(t_Scenarios[Volume_croisiere],3),H_VOLUME_M1+(INDEX(t_Scenarios[Volume_croisiere],3)-H_VOLUME_M1)*($A8-1)/(H_MONTEE-1))*H_COUT_USD -> -3834.2861
A9: =CALCULS!A9 -> 3 | B9: =(MIN(INDEX(t_Scenarios[Volume_croisiere],1),H_VOLUME_M1+(INDEX(t_Scenarios[Volume_croisiere],1)-H_VOLUME_M1)*($A9-1)/(H_MONTEE-1))*INDEX(t_Scenarios[Prix_XOF],1)-(H_LOYER_XOF+H_PERSONNEL_XOF+H_AUTRES_XOF))/(H_TAUX_XOF*(1+INDEX(t_Scenarios[Derive_Taux],1))^$A9)-MIN(INDEX(t_Scenarios[Volume_croisiere],1),H_VOLUME_M1+(INDEX(t_Scenarios[Volume_croisiere],1)-H_VOLUME_M1)*($A9-1)/(H_MONTEE-1))*H_COUT_USD -> -5393.9646 | C9: =(MIN(INDEX(t_Scenarios[Volume_croisiere],2),H_VOLUME_M1+(INDEX(t_Scenarios[Volume_croisiere],2)-H_VOLUME_M1)*($A9-1)/(H_MONTEE-1))*INDEX(t_Scenarios[Prix_XOF],2)-(H_LOYER_XOF+H_PERSONNEL_XOF+H_AUTRES_XOF))/(H_TAUX_XOF*(1+INDEX(t_Scenarios[Derive_Taux],2))^$A9)-MIN(INDEX(t_Scenarios[Volume_croisiere],2),H_VOLUME_M1+(INDEX(t_Scenarios[Volume_croisiere],2)-H_VOLUME_M1)*($A9-1)/(H_MONTEE-1))*H_COUT_USD -> -2694.6047 | D9: =(MIN(INDEX(t_Scenarios[Volume_croisiere],3),H_VOLUME_M1+(INDEX(t_Scenarios[Volume_croisiere],3)-H_VOLUME_M1)*($A9-1)/(H_MONTEE-1))*INDEX(t_Scenarios[Prix_XOF],3)-(H_LOYER_XOF+H_PERSONNEL_XOF+H_AUTRES_XOF))/(H_TAUX_XOF*(1+INDEX(t_Scenarios[Derive_Taux],3))^$A9)-MIN(INDEX(t_Scenarios[Volume_croisiere],3),H_VOLUME_M1+(INDEX(t_Scenarios[Volume_croisiere],3)-H_VOLUME_M1)*($A9-1)/(H_MONTEE-1))*H_COUT_USD -> -514.77546
A10: =CALCULS!A10 -> 4 | B10: =(MIN(INDEX(t_Scenarios[Volume_croisiere],1),H_VOLUME_M1+(INDEX(t_Scenarios[Volume_croisiere],1)-H_VOLUME_M1)*($A10-1)/(H_MONTEE-1))*INDEX(t_Scenarios[Prix_XOF],1)-(H_LOYER_XOF+H_PERSONNEL_XOF+H_AUTRES_XOF))/(H_TAUX_XOF*(1+INDEX(t_Scenarios[Derive_Taux],1))^$A10)-MIN(INDEX(t_Scenarios[Volume_croisiere],1),H_VOLUME_M1+(INDEX(t_Scenarios[Volume_croisiere],1)-H_VOLUME_M1)*($A10-1)/(H_MONTEE-1))*H_COUT_USD -> -3779.8833 | C10: =(MIN(INDEX(t_Scenarios[Volume_croisiere],2),H_VOLUME_M1+(INDEX(t_Scenarios[Volume_croisiere],2)-H_VOLUME_M1)*($A10-1)/(H_MONTEE-1))*INDEX(t_Scenarios[Prix_XOF],2)-(H_LOYER_XOF+H_PERSONNEL_XOF+H_AUTRES_XOF))/(H_TAUX_XOF*(1+INDEX(t_Scenarios[Derive_Taux],2))^$A10)-MIN(INDEX(t_Scenarios[Volume_croisiere],2),H_VOLUME_M1+(INDEX(t_Scenarios[Volume_croisiere],2)-H_VOLUME_M1)*($A10-1)/(H_MONTEE-1))*H_COUT_USD -> -207.09021 | D10: =(MIN(INDEX(t_Scenarios[Volume_croisiere],3),H_VOLUME_M1+(INDEX(t_Scenarios[Volume_croisiere],3)-H_VOLUME_M1)*($A10-1)/(H_MONTEE-1))*INDEX(t_Scenarios[Prix_XOF],3)-(H_LOYER_XOF+H_PERSONNEL_XOF+H_AUTRES_XOF))/(H_TAUX_XOF*(1+INDEX(t_Scenarios[Derive_Taux],3))^$A10)-MIN(INDEX(t_Scenarios[Volume_croisiere],3),H_VOLUME_M1+(INDEX(t_Scenarios[Volume_croisiere],3)-H_VOLUME_M1)*($A10-1)/(H_MONTEE-1))*H_COUT_USD -> 2766.5277
A11: =CALCULS!A11 -> 5 | B11: =(MIN(INDEX(t_Scenarios[Volume_croisiere],1),H_VOLUME_M1+(INDEX(t_Scenarios[Volume_croisiere],1)-H_VOLUME_M1)*($A11-1)/(H_MONTEE-1))*INDEX(t_Scenarios[Prix_XOF],1)-(H_LOYER_XOF+H_PERSONNEL_XOF+H_AUTRES_XOF))/(H_TAUX_XOF*(1+INDEX(t_Scenarios[Derive_Taux],1))^$A11)-MIN(INDEX(t_Scenarios[Volume_croisiere],1),H_VOLUME_M1+(INDEX(t_Scenarios[Volume_croisiere],1)-H_VOLUME_M1)*($A11-1)/(H_MONTEE-1))*H_COUT_USD -> -2261.1619 | C11: =(MIN(INDEX(t_Scenarios[Volume_croisiere],2),H_VOLUME_M1+(INDEX(t_Scenarios[Volume_croisiere],2)-H_VOLUME_M1)*($A11-1)/(H_MONTEE-1))*INDEX(t_Scenarios[Prix_XOF],2)-(H_LOYER_XOF+H_PERSONNEL_XOF+H_AUTRES_XOF))/(H_TAUX_XOF*(1+INDEX(t_Scenarios[Derive_Taux],2))^$A11)-MIN(INDEX(t_Scenarios[Volume_croisiere],2),H_VOLUME_M1+(INDEX(t_Scenarios[Volume_croisiere],2)-H_VOLUME_M1)*($A11-1)/(H_MONTEE-1))*H_COUT_USD -> 2209.6135 | D11: =(MIN(INDEX(t_Scenarios[Volume_croisiere],3),H_VOLUME_M1+(INDEX(t_Scenarios[Volume_croisiere],3)-H_VOLUME_M1)*($A11-1)/(H_MONTEE-1))*INDEX(t_Scenarios[Prix_XOF],3)-(H_LOYER_XOF+H_PERSONNEL_XOF+H_AUTRES_XOF))/(H_TAUX_XOF*(1+INDEX(t_Scenarios[Derive_Taux],3))^$A11)-MIN(INDEX(t_Scenarios[Volume_croisiere],3),H_VOLUME_M1+(INDEX(t_Scenarios[Volume_croisiere],3)-H_VOLUME_M1)*($A11-1)/(H_MONTEE-1))*H_COUT_USD -> 6009.7378
A12: =CALCULS!A12 -> 6 | B12: =(MIN(INDEX(t_Scenarios[Volume_croisiere],1),H_VOLUME_M1+(INDEX(t_Scenarios[Volume_croisiere],1)-H_VOLUME_M1)*($A12-1)/(H_MONTEE-1))*INDEX(t_Scenarios[Prix_XOF],1)-(H_LOYER_XOF+H_PERSONNEL_XOF+H_AUTRES_XOF))/(H_TAUX_XOF*(1+INDEX(t_Scenarios[Derive_Taux],1))^$A12)-MIN(INDEX(t_Scenarios[Volume_croisiere],1),H_VOLUME_M1+(INDEX(t_Scenarios[Volume_croisiere],1)-H_VOLUME_M1)*($A12-1)/(H_MONTEE-1))*H_COUT_USD -> -836.65962 | C12: =(MIN(INDEX(t_Scenarios[Volume_croisiere],2),H_VOLUME_M1+(INDEX(t_Scenarios[Volume_croisiere],2)-H_VOLUME_M1)*($A12-1)/(H_MONTEE-1))*INDEX(t_Scenarios[Prix_XOF],2)-(H_LOYER_XOF+H_PERSONNEL_XOF+H_AUTRES_XOF))/(H_TAUX_XOF*(1+INDEX(t_Scenarios[Derive_Taux],2))^$A12)-MIN(INDEX(t_Scenarios[Volume_croisiere],2),H_VOLUME_M1+(INDEX(t_Scenarios[Volume_croisiere],2)-H_VOLUME_M1)*($A12-1)/(H_MONTEE-1))*H_COUT_USD -> 4555.9834 | D12: =(MIN(INDEX(t_Scenarios[Volume_croisiere],3),H_VOLUME_M1+(INDEX(t_Scenarios[Volume_croisiere],3)-H_VOLUME_M1)*($A12-1)/(H_MONTEE-1))*INDEX(t_Scenarios[Prix_XOF],3)-(H_LOYER_XOF+H_PERSONNEL_XOF+H_AUTRES_XOF))/(H_TAUX_XOF*(1+INDEX(t_Scenarios[Derive_Taux],3))^$A12)-MIN(INDEX(t_Scenarios[Volume_croisiere],3),H_VOLUME_M1+(INDEX(t_Scenarios[Volume_croisiere],3)-H_VOLUME_M1)*($A12-1)/(H_MONTEE-1))*H_COUT_USD -> 9214.9691
A13: =CALCULS!A13 -> 7 | B13: =(MIN(INDEX(t_Scenarios[Volume_croisiere],1),H_VOLUME_M1+(INDEX(t_Scenarios[Volume_croisiere],1)-H_VOLUME_M1)*($A13-1)/(H_MONTEE-1))*INDEX(t_Scenarios[Prix_XOF],1)-(H_LOYER_XOF+H_PERSONNEL_XOF+H_AUTRES_XOF))/(H_TAUX_XOF*(1+INDEX(t_Scenarios[Derive_Taux],1))^$A13)-MIN(INDEX(t_Scenarios[Volume_croisiere],1),H_VOLUME_M1+(INDEX(t_Scenarios[Volume_croisiere],1)-H_VOLUME_M1)*($A13-1)/(H_MONTEE-1))*H_COUT_USD -> 494.75224 | C13: =(MIN(INDEX(t_Scenarios[Volume_croisiere],2),H_VOLUME_M1+(INDEX(t_Scenarios[Volume_croisiere],2)-H_VOLUME_M1)*($A13-1)/(H_MONTEE-1))*INDEX(t_Scenarios[Prix_XOF],2)-(H_LOYER_XOF+H_PERSONNEL_XOF+H_AUTRES_XOF))/(H_TAUX_XOF*(1+INDEX(t_Scenarios[Derive_Taux],2))^$A13)-MIN(INDEX(t_Scenarios[Volume_croisiere],2),H_VOLUME_M1+(INDEX(t_Scenarios[Volume_croisiere],2)-H_VOLUME_M1)*($A13-1)/(H_MONTEE-1))*H_COUT_USD -> 6832.4938 | D13: =(MIN(INDEX(t_Scenarios[Volume_croisiere],3),H_VOLUME_M1+(INDEX(t_Scenarios[Volume_croisiere],3)-H_VOLUME_M1)*($A13-1)/(H_MONTEE-1))*INDEX(t_Scenarios[Prix_XOF],3)-(H_LOYER_XOF+H_PERSONNEL_XOF+H_AUTRES_XOF))/(H_TAUX_XOF*(1+INDEX(t_Scenarios[Derive_Taux],3))^$A13)-MIN(INDEX(t_Scenarios[Volume_croisiere],3),H_VOLUME_M1+(INDEX(t_Scenarios[Volume_croisiere],3)-H_VOLUME_M1)*($A13-1)/(H_MONTEE-1))*H_COUT_USD -> 12382.335
A14: =CALCULS!A14 -> 8 | B14: =(MIN(INDEX(t_Scenarios[Volume_croisiere],1),H_VOLUME_M1+(INDEX(t_Scenarios[Volume_croisiere],1)-H_VOLUME_M1)*($A14-1)/(H_MONTEE-1))*INDEX(t_Scenarios[Prix_XOF],1)-(H_LOYER_XOF+H_PERSONNEL_XOF+H_AUTRES_XOF))/(H_TAUX_XOF*(1+INDEX(t_Scenarios[Derive_Taux],1))^$A14)-MIN(INDEX(t_Scenarios[Volume_croisiere],1),H_VOLUME_M1+(INDEX(t_Scenarios[Volume_croisiere],1)-H_VOLUME_M1)*($A14-1)/(H_MONTEE-1))*H_COUT_USD -> 1734.1904 | C14: =(MIN(INDEX(t_Scenarios[Volume_croisiere],2),H_VOLUME_M1+(INDEX(t_Scenarios[Volume_croisiere],2)-H_VOLUME_M1)*($A14-1)/(H_MONTEE-1))*INDEX(t_Scenarios[Prix_XOF],2)-(H_LOYER_XOF+H_PERSONNEL_XOF+H_AUTRES_XOF))/(H_TAUX_XOF*(1+INDEX(t_Scenarios[Derive_Taux],2))^$A14)-MIN(INDEX(t_Scenarios[Volume_croisiere],2),H_VOLUME_M1+(INDEX(t_Scenarios[Volume_croisiere],2)-H_VOLUME_M1)*($A14-1)/(H_MONTEE-1))*H_COUT_USD -> 9039.6159 | D14: =(MIN(INDEX(t_Scenarios[Volume_croisiere],3),H_VOLUME_M1+(INDEX(t_Scenarios[Volume_croisiere],3)-H_VOLUME_M1)*($A14-1)/(H_MONTEE-1))*INDEX(t_Scenarios[Prix_XOF],3)-(H_LOYER_XOF+H_PERSONNEL_XOF+H_AUTRES_XOF))/(H_TAUX_XOF*(1+INDEX(t_Scenarios[Derive_Taux],3))^$A14)-MIN(INDEX(t_Scenarios[Volume_croisiere],3),H_VOLUME_M1+(INDEX(t_Scenarios[Volume_croisiere],3)-H_VOLUME_M1)*($A14-1)/(H_MONTEE-1))*H_COUT_USD -> 15511.95
A15: =CALCULS!A15 -> 9 | B15: =(MIN(INDEX(t_Scenarios[Volume_croisiere],1),H_VOLUME_M1+(INDEX(t_Scenarios[Volume_croisiere],1)-H_VOLUME_M1)*($A15-1)/(H_MONTEE-1))*INDEX(t_Scenarios[Prix_XOF],1)-(H_LOYER_XOF+H_PERSONNEL_XOF+H_AUTRES_XOF))/(H_TAUX_XOF*(1+INDEX(t_Scenarios[Derive_Taux],1))^$A15)-MIN(INDEX(t_Scenarios[Volume_croisiere],1),H_VOLUME_M1+(INDEX(t_Scenarios[Volume_croisiere],1)-H_VOLUME_M1)*($A15-1)/(H_MONTEE-1))*H_COUT_USD -> 2882.7598 | C15: =(MIN(INDEX(t_Scenarios[Volume_croisiere],2),H_VOLUME_M1+(INDEX(t_Scenarios[Volume_croisiere],2)-H_VOLUME_M1)*($A15-1)/(H_MONTEE-1))*INDEX(t_Scenarios[Prix_XOF],2)-(H_LOYER_XOF+H_PERSONNEL_XOF+H_AUTRES_XOF))/(H_TAUX_XOF*(1+INDEX(t_Scenarios[Derive_Taux],2))^$A15)-MIN(INDEX(t_Scenarios[Volume_croisiere],2),H_VOLUME_M1+(INDEX(t_Scenarios[Volume_croisiere],2)-H_VOLUME_M1)*($A15-1)/(H_MONTEE-1))*H_COUT_USD -> 11177.818 | D15: =(MIN(INDEX(t_Scenarios[Volume_croisiere],3),H_VOLUME_M1+(INDEX(t_Scenarios[Volume_croisiere],3)-H_VOLUME_M1)*($A15-1)/(H_MONTEE-1))*INDEX(t_Scenarios[Prix_XOF],3)-(H_LOYER_XOF+H_PERSONNEL_XOF+H_AUTRES_XOF))/(H_TAUX_XOF*(1+INDEX(t_Scenarios[Derive_Taux],3))^$A15)-MIN(INDEX(t_Scenarios[Volume_croisiere],3),H_VOLUME_M1+(INDEX(t_Scenarios[Volume_croisiere],3)-H_VOLUME_M1)*($A15-1)/(H_MONTEE-1))*H_COUT_USD -> 18603.927
A16: =CALCULS!A16 -> 10 | B16: =(MIN(INDEX(t_Scenarios[Volume_croisiere],1),H_VOLUME_M1+(INDEX(t_Scenarios[Volume_croisiere],1)-H_VOLUME_M1)*($A16-1)/(H_MONTEE-1))*INDEX(t_Scenarios[Prix_XOF],1)-(H_LOYER_XOF+H_PERSONNEL_XOF+H_AUTRES_XOF))/(H_TAUX_XOF*(1+INDEX(t_Scenarios[Derive_Taux],1))^$A16)-MIN(INDEX(t_Scenarios[Volume_croisiere],1),H_VOLUME_M1+(INDEX(t_Scenarios[Volume_croisiere],1)-H_VOLUME_M1)*($A16-1)/(H_MONTEE-1))*H_COUT_USD -> 3941.5535 | C16: =(MIN(INDEX(t_Scenarios[Volume_croisiere],2),H_VOLUME_M1+(INDEX(t_Scenarios[Volume_croisiere],2)-H_VOLUME_M1)*($A16-1)/(H_MONTEE-1))*INDEX(t_Scenarios[Prix_XOF],2)-(H_LOYER_XOF+H_PERSONNEL_XOF+H_AUTRES_XOF))/(H_TAUX_XOF*(1+INDEX(t_Scenarios[Derive_Taux],2))^$A16)-MIN(INDEX(t_Scenarios[Volume_croisiere],2),H_VOLUME_M1+(INDEX(t_Scenarios[Volume_croisiere],2)-H_VOLUME_M1)*($A16-1)/(H_MONTEE-1))*H_COUT_USD -> 13247.567 | D16: =(MIN(INDEX(t_Scenarios[Volume_croisiere],3),H_VOLUME_M1+(INDEX(t_Scenarios[Volume_croisiere],3)-H_VOLUME_M1)*($A16-1)/(H_MONTEE-1))*INDEX(t_Scenarios[Prix_XOF],3)-(H_LOYER_XOF+H_PERSONNEL_XOF+H_AUTRES_XOF))/(H_TAUX_XOF*(1+INDEX(t_Scenarios[Derive_Taux],3))^$A16)-MIN(INDEX(t_Scenarios[Volume_croisiere],3),H_VOLUME_M1+(INDEX(t_Scenarios[Volume_croisiere],3)-H_VOLUME_M1)*($A16-1)/(H_MONTEE-1))*H_COUT_USD -> 21658.379
A17: =CALCULS!A17 -> 11 | B17: =(MIN(INDEX(t_Scenarios[Volume_croisiere],1),H_VOLUME_M1+(INDEX(t_Scenarios[Volume_croisiere],1)-H_VOLUME_M1)*($A17-1)/(H_MONTEE-1))*INDEX(t_Scenarios[Prix_XOF],1)-(H_LOYER_XOF+H_PERSONNEL_XOF+H_AUTRES_XOF))/(H_TAUX_XOF*(1+INDEX(t_Scenarios[Derive_Taux],1))^$A17)-MIN(INDEX(t_Scenarios[Volume_croisiere],1),H_VOLUME_M1+(INDEX(t_Scenarios[Volume_croisiere],1)-H_VOLUME_M1)*($A17-1)/(H_MONTEE-1))*H_COUT_USD -> 4911.653 | C17: =(MIN(INDEX(t_Scenarios[Volume_croisiere],2),H_VOLUME_M1+(INDEX(t_Scenarios[Volume_croisiere],2)-H_VOLUME_M1)*($A17-1)/(H_MONTEE-1))*INDEX(t_Scenarios[Prix_XOF],2)-(H_LOYER_XOF+H_PERSONNEL_XOF+H_AUTRES_XOF))/(H_TAUX_XOF*(1+INDEX(t_Scenarios[Derive_Taux],2))^$A17)-MIN(INDEX(t_Scenarios[Volume_croisiere],2),H_VOLUME_M1+(INDEX(t_Scenarios[Volume_croisiere],2)-H_VOLUME_M1)*($A17-1)/(H_MONTEE-1))*H_COUT_USD -> 15249.325 | D17: =(MIN(INDEX(t_Scenarios[Volume_croisiere],3),H_VOLUME_M1+(INDEX(t_Scenarios[Volume_croisiere],3)-H_VOLUME_M1)*($A17-1)/(H_MONTEE-1))*INDEX(t_Scenarios[Prix_XOF],3)-(H_LOYER_XOF+H_PERSONNEL_XOF+H_AUTRES_XOF))/(H_TAUX_XOF*(1+INDEX(t_Scenarios[Derive_Taux],3))^$A17)-MIN(INDEX(t_Scenarios[Volume_croisiere],3),H_VOLUME_M1+(INDEX(t_Scenarios[Volume_croisiere],3)-H_VOLUME_M1)*($A17-1)/(H_MONTEE-1))*H_COUT_USD -> 24675.418
A18: =CALCULS!A18 -> 12 | B18: =(MIN(INDEX(t_Scenarios[Volume_croisiere],1),H_VOLUME_M1+(INDEX(t_Scenarios[Volume_croisiere],1)-H_VOLUME_M1)*($A18-1)/(H_MONTEE-1))*INDEX(t_Scenarios[Prix_XOF],1)-(H_LOYER_XOF+H_PERSONNEL_XOF+H_AUTRES_XOF))/(H_TAUX_XOF*(1+INDEX(t_Scenarios[Derive_Taux],1))^$A18)-MIN(INDEX(t_Scenarios[Volume_croisiere],1),H_VOLUME_M1+(INDEX(t_Scenarios[Volume_croisiere],1)-H_VOLUME_M1)*($A18-1)/(H_MONTEE-1))*H_COUT_USD -> 5794.1283 | C18: =(MIN(INDEX(t_Scenarios[Volume_croisiere],2),H_VOLUME_M1+(INDEX(t_Scenarios[Volume_croisiere],2)-H_VOLUME_M1)*($A18-1)/(H_MONTEE-1))*INDEX(t_Scenarios[Prix_XOF],2)-(H_LOYER_XOF+H_PERSONNEL_XOF+H_AUTRES_XOF))/(H_TAUX_XOF*(1+INDEX(t_Scenarios[Derive_Taux],2))^$A18)-MIN(INDEX(t_Scenarios[Volume_croisiere],2),H_VOLUME_M1+(INDEX(t_Scenarios[Volume_croisiere],2)-H_VOLUME_M1)*($A18-1)/(H_MONTEE-1))*H_COUT_USD -> 17183.551 | D18: =(MIN(INDEX(t_Scenarios[Volume_croisiere],3),H_VOLUME_M1+(INDEX(t_Scenarios[Volume_croisiere],3)-H_VOLUME_M1)*($A18-1)/(H_MONTEE-1))*INDEX(t_Scenarios[Prix_XOF],3)-(H_LOYER_XOF+H_PERSONNEL_XOF+H_AUTRES_XOF))/(H_TAUX_XOF*(1+INDEX(t_Scenarios[Derive_Taux],3))^$A18)-MIN(INDEX(t_Scenarios[Volume_croisiere],3),H_VOLUME_M1+(INDEX(t_Scenarios[Volume_croisiere],3)-H_VOLUME_M1)*($A18-1)/(H_MONTEE-1))*H_COUT_USD -> 27655.157
... A30: =CALCULS!A30 -> 24 | B30: =(MIN(INDEX(t_Scenarios[Volume_croisiere],1),H_VOLUME_M1+(INDEX(t_Scenarios[Volume_croisiere],1)-H_VOLUME_M1)*($A30-1)/(H_MONTEE-1))*INDEX(t_Scenarios[Prix_XOF],1)-(H_LOYER_XOF+H_PERSONNEL_XOF+H_AUTRES_XOF))/(H_TAUX_XOF*(1+INDEX(t_Scenarios[Derive_Taux],1))^$A30)-MIN(INDEX(t_Scenarios[Volume_croisiere],1),H_VOLUME_M1+(INDEX(t_Scenarios[Volume_croisiere],1)-H_VOLUME_M1)*($A30-1)/(H_MONTEE-1))*H_COUT_USD -> 991.31383 | C30: =(MIN(INDEX(t_Scenarios[Volume_croisiere],2),H_VOLUME_M1+(INDEX(t_Scenarios[Volume_croisiere],2)-H_VOLUME_M1)*($A30-1)/(H_MONTEE-1))*INDEX(t_Scenarios[Prix_XOF],2)-(H_LOYER_XOF+H_PERSONNEL_XOF+H_AUTRES_XOF))/(H_TAUX_XOF*(1+INDEX(t_Scenarios[Derive_Taux],2))^$A30)-MIN(INDEX(t_Scenarios[Volume_croisiere],2),H_VOLUME_M1+(INDEX(t_Scenarios[Volume_croisiere],2)-H_VOLUME_M1)*($A30-1)/(H_MONTEE-1))*H_COUT_USD -> 16040.184 | D30: =(MIN(INDEX(t_Scenarios[Volume_croisiere],3),H_VOLUME_M1+(INDEX(t_Scenarios[Volume_croisiere],3)-H_VOLUME_M1)*($A30-1)/(H_MONTEE-1))*INDEX(t_Scenarios[Prix_XOF],3)-(H_LOYER_XOF+H_PERSONNEL_XOF+H_AUTRES_XOF))/(H_TAUX_XOF*(1+INDEX(t_Scenarios[Derive_Taux],3))^$A30)-MIN(INDEX(t_Scenarios[Volume_croisiere],3),H_VOLUME_M1+(INDEX(t_Scenarios[Volume_croisiere],3)-H_VOLUME_M1)*($A30-1)/(H_MONTEE-1))*H_COUT_USD -> 30860.278
A33: Table de données à deux entrées — VAN en USD
A34: 420 simulations. En ligne les volumes de croisière, en colonne le taux de change de départ.
A36: VAN | B36: 15000 | C36: 15500 | D36: 16000 | E36: 16500 | F36: 17000 | G36: 17500 | H36: 18000 | I36: 18500 | J36: 19000 | K36: 19500 | L36: 20000 | M36: 20500 | N36: 21000 | O36: 21500 | P36: 22000 | Q36: 22500 | R36: 23000 | S36: 23500 | T36: 24000 | U36: 24500
A37: 600 | B37: -24719.65 | C37: -8756.34 | D37: 7206.96 | E37: 23170.26 | F37: 39133.57 | G37: 55096.87 | H37: 71060.18 | I37: 87023.48 | J37: 102986.78 | K37: 118950.09 | L37: 134913.39 | M37: 150876.7 | N37: 166840 | O37: 182803.3 | P37: 198766.61 | Q37: 214729.91 | R37: 230693.21 | S37: 246656.52 | T37: 262619.82 | U37: 278583.13
A38: 605 | B38: -35355.91 | C38: -19794.64 | D38: -4233.36 | E38: 11327.91 | F38: 26889.18 | G38: 42450.46 | H38: 58011.73 | I38: 73573 | J38: 89134.28 | K38: 104695.55 | L38: 120256.83 | M38: 135818.1 | N38: 151379.37 | O38: 166940.65 | P38: 182501.92 | Q38: 198063.19 | R38: 213624.47 | S38: 229185.74 | T38: 244747.02 | U38: 260308.29
A39: 610 | B39: -45817.81 | C39: -30651.98 | D39: -15486.14 | E39: -320.31 | F39: 14845.53 | G39: 30011.36 | H39: 45177.19 | I39: 60343.03 | J39: 75508.86 | K39: 90674.7 | L39: 105840.53 | M39: 121006.37 | N39: 136172.2 | O39: 151338.04 | P39: 166503.87 | Q39: 181669.7 | R39: 196835.54 | S39: 212001.37 | T39: 227167.21 | U39: 242333.04
A40: 615 | B40: -56109.6 | C40: -41332.77 | D40: -26555.95 | E40: -11779.12 | F40: 2997.7 | G40: 17774.53 | H40: 32551.35 | I40: 47328.18 | J40: 62105 | K40: 76881.82 | L40: 91658.65 | M40: 106435.47 | N40: 121212.3 | O40: 135989.12 | P40: 150765.95 | Q40: 165542.77 | R40: 180319.6 | S40: 195096.42 | T40: 209873.25 | U40: 224650.07
A41: 620 | B41: -66235.39 | C41: -51841.3 | D41: -37447.21 | E41: -23053.12 | F41: -8659.03 | G41: 5735.06 | H41: 20129.15 | I41: 34523.24 | J41: 48917.33 | K41: 63311.42 | L41: 77705.51 | M41: 92099.6 | N41: 106493.69 | O41: 120887.78 | P41: 135281.87 | Q41: 149675.96 | R41: 164070.05 | S41: 178464.14 | T41: 192858.22 | U41: 207252.31
A42: 625 | B42: -76199.17 | C42: -62181.69 | D42: -48164.21 | E42: -34146.73 | F42: -20129.25 | G42: -6111.78 | H42: 7905.7 | I42: 21923.18 | J42: 35940.66 | K42: 49958.14 | L42: 63975.61 | M42: 77993.09 | N42: 92010.57 | O42: 106028.05 | P42: 120045.53 | Q42: 134063.01 | R42: 148080.48 | S42: 162097.96 | T42: 176115.44 | U42: 190132.92
A43: 630 | B43: -86004.79 | C43: -72357.95 | D43: -58711.1 | E43: -45064.26 | F43: -31417.41 | G43: -17770.57 | H43: -4123.72 | I43: 9523.12 | J43: 23169.97 | K43: 36816.81 | L43: 50463.66 | M43: 64110.5 | N43: 77757.35 | O43: 91404.19 | P43: 105051.04 | Q43: 118697.88 | R43: 132344.73 | S43: 145991.57 | T43: 159638.42 | U43: 173285.26
A44: 635 | B44: -95655.99 | C44: -82373.95 | D44: -69091.9 | E44: -55809.85 | F44: -42527.8 | G44: -29245.75 | H44: -15963.71 | I44: -2681.66 | J44: 10600.39 | K44: 23882.44 | L44: 37164.49 | M44: 50446.53 | N44: 63728.58 | O44: 77010.63 | P44: 90292.68 | Q44: 103574.73 | R44: 116856.78 | S44: 130138.82 | T44: 143420.87 | U44: 156702.92
A45: 640 | B45: -105156.4 | C45: -92233.45 | D45: -79310.5 | E45: -66387.54 | F45: -53464.59 | G45: -40541.64 | H45: -27618.69 | I45: -14695.74 | J45: -1772.79 | K45: 11150.16 | L45: 24073.12 | M45: 36996.07 | N45: 49919.02 | O45: 62841.97 | P45: 75764.92 | Q45: 88687.87 | R45: 101610.82 | S45: 114533.78 | T45: 127456.73 | U45: 140379.68
A46: 645 | B46: -114509.51 | C46: -101940.09 | D46: -89370.67 | E46: -76801.24 | F46: -64231.82 | G46: -51662.4 | H46: -39092.98 | I46: -26523.55 | J46: -13954.13 | K46: -1384.71 | L46: 11184.71 | M46: 23754.13 | N46: 36323.56 | O46: 48892.98 | P46: 61462.4 | Q46: 74031.82 | R46: 86601.24 | S46: 99170.67 | T46: 111740.09 | U46: 124309.51
A47: 650 | B47: -123718.73 | C47: -111497.39 | D47: -99276.06 | E47: -87054.73 | F47: -74833.4 | G47: -62612.07 | H47: -50390.74 | I47: -38169.4 | J47: -25948.07 | K47: -13726.74 | L47: -1505.41 | M47: 10715.92 | N47: 22937.25 | O47: 35158.59 | P47: 47379.92 | Q47: 59601.25 | R47: 71822.58 | S47: 84043.91 | T47: 96265.24 | U47: 108486.58
A48: 655 | B48: -132787.34 | C48: -120908.79 | D48: -109030.23 | E48: -97151.68 | F48: -85273.12 | G48: -73394.57 | H48: -61516.01 | I48: -49637.45 | J48: -37758.9 | K48: -25880.34 | L48: -14001.79 | M48: -2123.23 | N48: 9755.32 | O48: 21633.88 | P48: 33512.43 | Q48: 45390.99 | R48: 57269.55 | S48: 69148.1 | T48: 81026.66 | U48: 92905.21
... A57: 700 | B57: -208575.08 | C57: -199561.15 | D57: -190547.23 | E57: -181533.3 | F57: -172519.37 | G57: -163505.44 | H57: -154491.52 | I57: -145477.59 | J57: -136463.66 | K57: -127449.74 | L57: -118435.81 | M57: -109421.88 | N57: -100407.96 | O57: -91394.03 | P57: -82380.1 | Q57: -73366.18 | R57: -64352.25 | S57: -55338.32 | T57: -46324.4 | U57: -37310.47

Sheet DASHBOARD
A1: Bamako — la décision en une page
A2: Neuf chiffres. Si la direction en veut un dixième, c'est que l'un des neuf ne répond pas.
A4: Investissement | B4: =REPONSES!$B$11 -> 204500
A5: VAN à 14 % | B5: =REPONSES!$B$23 -> 33174.539
A6: TRI annuel | B6: =REPONSES!$B$24 -> 0.27099378
A7: Retour sur investissement | B7: =REPONSES!$B$27 -> 20
A8: Seuil mensuel | B8: =REPONSES!$B$25 -> 7549
A9: Taux limite | B9: =REPONSES!$B$32 -> 644.44382
A10: Marge de sécurité | B10: =REPONSES!$B$33 -> 0.020658571
A11: VAN pessimiste | B11: =REPONSES!$B$29 -> -171318.39
A12: VAN optimiste | B12: =REPONSES!$B$30 -> 223831.83
A15: La phrase à dire en réunion
A16: Le projet est rentable au plan de base, et il cesse de l'être si le franc CFA part de 644 au lieu de 631.40 — soit 2.1 % de marge. Le reste se discute ; ça, non.

Sheet QUALITE
A1: Contrôles de qualité
A2: Huit contrôles. Tant qu'un seul ne passe pas, le modèle n'est pas prêt à sortir.
A4: Contrôle | B4: Valeur | C4: Ce que ça veut dire
A5: Hypothèses renseignées · doit valoir 14 | B5: =COUNT(HYPOTHESES!$B$5:$B$18) -> 14 | C5: quatorze, ni plus ni moins : une hypothèse de plus est une hypothèse cachée
A6: Hypothèses manquantes · doit valoir 0 | B6: =14-COUNT(HYPOTHESES!$B$5:$B$18) -> 0 | C6: le même contrôle, écrit dans le sens où on le lit
A7: Volume du mois 24 moins la croisière · doit valoir 0 | B7: =ROUND(INDEX(F_VOLUME,24)-H_VOLUME_CROISIERE,0) -> 0 | C7: si la montée en charge n'atteint jamais la croisière, la courbe est fausse
A8: Cumul du mois 24 moins la somme des flux · doit valoir 0 | B8: =ROUND(INDEX(F_CUMUL,25)-(SUM(F_FLUX1)-REPONSES!$B$11),2) -> 0 | C8: le cumul et la somme doivent tomber d'accord, sinon une ligne a glissé
A9: Scénario Base moins l'hypothèse de volume · doit valoir 0 | B9: =ROUND(INDEX(t_Scenarios[Volume_croisiere],2)-H_VOLUME_CROISIERE,0) -> 0 | C9: le scénario de base EST le plan : deux chiffres, une vérité
A10: Scénario Base moins l'hypothèse de prix · doit valoir 0 | B10: =ROUND(INDEX(t_Scenarios[Prix_XOF],2)-H_PRIX_XOF,0) -> 0 | C10: le piège classique : on modifie une hypothèse et on oublie le scénario
A11: La VAN est-elle positive ? | B11: =IF(REPONSES!$B$23>0,"PASS","FAIL") -> PASS | C11: PASS ne veut pas dire « il faut y aller » : lisez la marge de sécurité
A12: Les trois scénarios sont-ils ordonnés ? | B12: =IF(AND(REPONSES!$B$29<REPONSES!$B$23,REPONSES!$B$23<REPONSES!$B$30),"PASS","FAIL") -> PASS | C12: pessimiste < base < optimiste : sinon un paramètre est inversé

Sheet REPONSES
A1: TP 9 — La septième agence
A2: Les cellules jaunes se remplissent une fois le modèle construit. Les trois premières se lisent dans les outils ; les autres se calculent.
A4: ① CE QUE VOUS LISEZ DANS LES OUTILS
A5: Taux limite trouvé par Valeur cible, en XOF pour 1 USD | B5: 644.44
A6: VAN du scénario pessimiste, lue dans le rapport de synthèse | B6: -171318.39
A7: VAN au croisement taux 660 / volume 18 000 de la table de données | B7: -72472.72
A9: ② CE QUE LES FORMULES VÉRIFIENT
A11: Investissement initial total | B11: =H_AMENAGEMENT+H_MATERIEL+H_STOCK_INITIAL -> 204500
A12: Charges fixes mensuelles | B12: =H_LOYER_XOF+H_PERSONNEL_XOF+H_AUTRES_XOF -> 11150000
A13: Taux d'actualisation mensuel | B13: =(1+H_ACTUALISATION)^(1/12)-1 -> 0.010978852
A14: Taux de change au mois 24 | B14: =H_TAUX_XOF*(1+H_DERIVE_TAUX)^24 -> 703.23935
A15: Volume total vendu sur 24 mois | B15: =SUM(F_VOLUME) -> 360900
A16: Volume du mois 12 | B16: =INDEX(F_VOLUME,12) -> 17146.154
A17: Chiffre d'affaires cumulé, en USD | B17: =SUM(F_CA_USD) -> 2328209.6
A18: Achats cumulés, en USD | B18: =SUM(F_ACHATS) -> 1642095
A19: Charges cumulées, en USD | B19: =SUM(F_CHARGES_USD) -> 400882.41
A20: Marge brute cumulée, en USD | B20: =B17-B18 -> 686114.62
A21: Taux de marge brute moyen | B21: =1-B18/B17 -> 0.29469624
A22: Résultat cumulé sur 24 mois, en USD | B22: =SUM(F_FLUX1) -> 285232.21
A23: VAN du projet, en USD · le flux du mois 0 n'entre pas dans VAN | B23: =NPV(B13,F_FLUX1)-B11 -> 33174.539
A24: TRI annuel du projet | B24: =(1+IRR(F_FLUX))^12-1 -> 0.27099378
A25: Seuil de rentabilité mensuel, en unités | B25: =ROUNDUP(B12/(H_PRIX_XOF-H_COUT_USD*H_TAUX_XOF),0) -> 7549
A26: Mois où le volume de croisière est atteint | B26: =COUNTIF(F_VOLUME,"<"&H_VOLUME_CROISIERE)+1 -> 14
A27: Mois de retour sur investissement | B27: =COUNTIF(F_CUMUL,"<0") -> 20
A28: Meilleur mois en résultat, en USD | B28: =MAX(F_FLUX1) -> 20851.239
A29: VAN du scénario pessimiste | B29: =NPV(B13,S_FLUX_PESS)-B11 -> -171318.39
A30: VAN du scénario optimiste | B30: =NPV(B13,S_FLUX_OPT)-B11 -> 223831.83
A31: Écart entre optimiste et pessimiste | B31: =B30-B29 -> 395150.22
A32: 💎 Taux de change au-delà duquel le projet devient perdant | B32: =H_TAUX_XOF*SUMPRODUCT(F_MARGE_USD,F_ACTU)/(B11+SUMPRODUCT(F_ACHATS,F_ACTU)) -> 644.44382
A33: Marge de sécurité sur le taux de change | B33: =B32/H_TAUX_XOF-1 -> 0.020658571
A34: Valeurs en dur hors HYPOTHESES · doit valoir 0 | B34: =SUMPRODUCT((Z_AUDIT<>"")*NOT(_xlfn.ISFORMULA(Z_AUDIT))) -> 0
A35: R_ECART_TAUX — Valeur cible moins formule · doit valoir 0 | B35: =ROUND(B5-B32,0) -> 0
A36: R_CONTROLE — résultat moins (CA − achats − charges) · doit valoir 0 | B36: =ROUND(B22-(B17-B18-B19),2) -> 0

Sheet ANNEXE_IA
A1: ANNEXE_IA
A3: Le prompt de cadrage | B3: Ce que vous avez demandé pour obtenir la liste des hypothèses à chiffrer, avant d'écrire la moindre formule.
A4: Le prompt de structure | B4: Ce que vous avez demandé pour obtenir l'architecture du classeur.
A5: L'erreur de l'IA | B5: Ce qu'elle a proposé et qui était faux ou incomplet, et comment vous l'avez attrapé. Au moins une erreur, décrite précisément.
A6: Le V qui l'a attrapée | B6: V1 source · V2 calcul · V3 cohérence · V4 terrain · V5 lisibilité.
A7: Ce que vous n'avez pas suivi | B7: Une suggestion de l'IA que vous avez écartée, et pourquoi.
